mdonatello/__init__.py
mdonatello/drawer.py
mdonatello/mapper.py
mdonatello/mdonatello.py
mdonatello/properties.py
mdonatello/data/README.md
mdonatello/data/__init__.py
mdonatello/data/files.py
mdonatello/data/input.pdb
mdonatello/data/mda.txt
mdonatello/tests/__init__.py
mdonatello/tests/conftest.py
mdonatello/tests/test_drawer.py
mdonatello/tests/test_mapper.py
mdonatello/tests/test_mdonatello.py
mdonatello/tests/utils.py
mdonatello-0.0.1.dist-info/AUTHORS.md
mdonatello-0.0.1.dist-info/LICENSE
mdonatello-0.0.1.dist-info/METADATA
mdonatello-0.0.1.dist-info/WHEEL
mdonatello-0.0.1.dist-info/top_level.txt
mdonatello-0.0.1.dist-info/RECORD
