Metadata-Version: 2.1
Name: mdonatello
Version: 0.0.1
Summary: 2D small molecule visualization for MDAnalysis
Author-email: Valerij Talagayev <v.talagayev@fu-berlin.de>
Maintainer-email: Valerij Talagayev <v.talagayev@fu-berlin.de>
License: GNU GENERAL PUBLIC LICENSE
Keywords: molecular simulations
Requires-Python: >=3.9
License-File: LICENSE
License-File: AUTHORS.md
Requires-Dist: MDAnalysis >=2.0.0
Requires-Dist: notebook
Requires-Dist: ipywidgets
Requires-Dist: rdkit
Provides-Extra: doc
Requires-Dist: sphinx ; extra == 'doc'
Requires-Dist: sphinx-rtd-theme ; extra == 'doc'
Provides-Extra: test
Requires-Dist: pytest >=6.0 ; extra == 'test'
Requires-Dist: pytest-xdist >=2.5 ; extra == 'test'
Requires-Dist: pytest-cov >=3.0 ; extra == 'test'
